{"papers_index.md":"DbbGIk33","posts_index.md":"wloWo_MZ","research_index.md":"nVbas4Py","people_leyao-wang.md":"Crkw6c4V","people_jie-zhu.md":"BHT2dZ_k","people_index.md":"D-QMvmmB","projects_index.md":"zNc9Ub96","research_research-aims.md":"BX2BjeLQ","people_lin-qu.md":"Dw4MlQfX","people_haiming-li.md":"B0KfbwIx","people_dongmei-wen.md":"aX1xinEi","posts_2025-08-26_haiming-li_work.md":"BaBfMx8z","index.md":"Ltrs_w_l","join_index.md":"C8p7_7od","readme.md":"IELU5o36","posts_2025-08-26_team-meet.md":"OrLgkv-x"}
